aspectreat/__init__.py
aspectreat/main.py
aspectreat/aspectreat_pcs/__init__.py
aspectreat/aspectreat_pcs/et.py
aspectreat/pyarmor_runtime_000000/__init__.py
aspectreat/pyarmor_runtime_000000/pyarmor_runtime.so
aspectreat-1.0.6.dist-info/LICENSE.txt
aspectreat-1.0.6.dist-info/METADATA
aspectreat-1.0.6.dist-info/WHEEL
aspectreat-1.0.6.dist-info/top_level.txt
aspectreat-1.0.6.dist-info/RECORD
