Metadata-Version: 2.1
Name: aspectreat
Version: 1.0.6
Summary: This is a project template.
Author: lylake
Classifier: Topic :: Software Development :: Libraries :: Python Modules
Classifier: Development Status :: 4 - Beta
Classifier: License :: OSI Approved :: Mozilla Public License 2.0 (MPL 2.0)
Classifier: Programming Language :: Python :: 3
Classifier: Programming Language :: Python :: 3.3
Classifier: Programming Language :: Python :: 3.4
Classifier: Programming Language :: Python :: 3.5
Classifier: Programming Language :: Python :: 3.6
Classifier: Programming Language :: Python :: 3.7
Classifier: Programming Language :: Python :: 3.8
Classifier: Programming Language :: Python :: 3.9
Classifier: Operating System :: Microsoft :: Windows
Classifier: Intended Audience :: End Users/Desktop
Classifier: Natural Language :: English
Classifier: Natural Language :: Chinese (Simplified)
License-File: LICENSE.txt
Requires-Dist: passlib >=1.7.4
Requires-Dist: pathspec >=0.12.1
Requires-Dist: pefile >=2023.2.7
Requires-Dist: pillow >=10.1.0
Requires-Dist: face-recognition ==1.3.0
Requires-Dist: rsa ==4.9
Requires-Dist: scipy ==1.11.4
Requires-Dist: setuptools >=68.0.0
Requires-Dist: six >=1.16.0
